{
    "session_started":  "2026-07-03T14:15:12.7872025+03:00",
    "positions":  [
                      {
                          "symbol":  "SOL/USD",
                          "qty":  63.44633463,
                          "entry_price":  81.47,
                          "atr":  9.4725,
                          "managed_mode":  "crypto_dynamic",
                          "protective_type":  "fixed",
                          "protective_order_id":  "81f6f089-c03e-4e10-8c43-a14a31f25f54",
                          "stop_price":  71.1849,
                          "breakeven_trigger":  90.415,
                          "trail_trigger":  99.3575,
                          "trail_percent":  8,
                          "rung1_fired":  false,
                          "rung1_trigger":  67.3175,
                          "rung1_qty":  47.584751,
                          "rung2_fired":  false,
                          "rung2_trigger":  57.8825,
                          "rung2_qty":  79.307919,
                          "order_id":  "262ccf55-b42f-4ae5-8278-7be32e49029a",
                          "opened_at":  "2026-07-03T14:15:12.7881902+03:00",
                          "total_score":  6.5,
                          "tech_score":  6.5,
                          "news_score":  0,
                          "signal":  "STRONG_BUY"
                      },
                      {
                          "symbol":  "ETH/USD",
                          "qty":  3.78701274,
                          "entry_price":  1739.9,
                          "atr":  158.72,
                          "managed_mode":  "crypto_dynamic",
                          "protective_type":  "fixed",
                          "protective_order_id":  "732d0acc-eaf1-4536-8b7d-274bef4d6431",
                          "stop_price":  1540.46,
                          "breakeven_trigger":  2057.34,
                          "trail_trigger":  2374.78,
                          "trail_percent":  8,
                          "rung1_fired":  false,
                          "rung1_trigger":  1263.26,
                          "rung1_qty":  2.84026,
                          "rung2_fired":  false,
                          "rung2_trigger":  945.82,
                          "rung2_qty":  4.733766,
                          "order_id":  "ea9c73d2-671c-413c-b1c4-33d769aadba2",
                          "opened_at":  "2026-07-03T14:15:12.7891877+03:00",
                          "total_score":  6,
                          "tech_score":  6,
                          "news_score":  0,
                          "signal":  "BUY"
                      }
                  ],
    "entries_made":  2
}
